MANIFEST.in
README.md
setup.py
test_push_swap/__init__.py
test_push_swap/post_install.py
test_push_swap/pstester.py
test_push_swap/setup.py
test_push_swap/test-push-swap.py
test_push_swap/test_push_swap.py
test_push_swap.egg-info/PKG-INFO
test_push_swap.egg-info/SOURCES.txt
test_push_swap.egg-info/dependency_links.txt
test_push_swap.egg-info/entry_points.txt
test_push_swap.egg-info/top_level.txt