Metadata-Version: 2.1
Name: test-push-swap
Version: 0.4
Summary: A tester for the push swap project
Home-page: https://github.com/hu8813/tester_push_swap
Author: hueseyin kaya aydin
Author-email: huaydin@student.42vienna.com
License: MIT
Platform: UNKNOWN
